my_own_package/__init__.py
my_own_package-0.1.0.dist-info/METADATA
my_own_package-0.1.0.dist-info/WHEEL
my_own_package-0.1.0.dist-info/top_level.txt
my_own_package-0.1.0.dist-info/RECORD
