Metadata-Version: 2.1
Name: my-own-package
Version: 0.1.0
Summary: my_first_package
Author: Alex Moldovan
Author-email: alex_moldovan1@yahoo.com
